{"inkVersion":21,"root":[["\n",{"->":"Start"},["done",{"#f":5,"#n":"g-0"}],null],"done",{"Start":[["^Hello? Is this okay?","\n",["ev",{"^->":"Start.0.2.$r1"},{"temp=":"$r"},"str",{"->":".^.s"},[{"#n":"$r1"}],"/str","/ev",{"*":".^.^.c-0","flg":18},{"s":["^Hello and welcome to ASOS",{"->":"$r","var":true},null]}],["ev",{"^->":"Start.0.3.$r1"},{"temp=":"$r"},"str",{"->":".^.s"},[{"#n":"$r1"}],"/str","/ev",{"*":".^.^.c-1","flg":18},{"s":["^Is what okay?",{"->":"$r","var":true},null]}],["ev",{"^->":"Start.0.4.$r1"},{"temp=":"$r"},"str",{"->":".^.s"},[{"#n":"$r1"}],"/str","/ev",{"*":".^.^.c-2","flg":18},{"s":["^Yes, I can hear you fine.",{"->":"$r","var":true},null]}],["ev",{"^->":"Start.0.5.$r1"},{"temp=":"$r"},"str",{"->":".^.s"},[{"#n":"$r1"}],"/str","/ev",{"*":".^.^.c-3","flg":18},{"s":["^...Me?",{"->":"$r","var":true},null]}],["ev",{"^->":"Start.0.6.$r1"},{"temp=":"$r"},"str",{"->":".^.s"},[{"#n":"$r1"}],"/str","/ev",{"*":".^.^.c-4","flg":18},{"s":["^Hi Chamomile.",{"->":"$r","var":true},null]}],["ev",{"^->":"Start.0.7.$r1"},{"temp=":"$r"},"str",{"->":".^.s"},[{"#n":"$r1"}],"/str","/ev",{"*":".^.^.c-5","flg":18},{"s":["^Well Ma'am, the first step",{"->":"$r","var":true},null]}],["ev",{"^->":"Start.0.8.$r1"},{"temp=":"$r"},"str",{"->":".^.s"},[{"#n":"$r1"}],"/str","/ev",{"*":".^.^.c-6","flg":18},{"s":["^Okay, so",{"->":"$r","var":true},null]}],{"c-0":["ev",{"^->":"Start.0.c-0.$r2"},"/ev",{"temp=":"$r"},{"->":".^.^.2.s"},[{"#n":"$r2"}],"^ How can I help you today?","\n",{"#f":5}],"c-1":["ev",{"^->":"Start.0.c-1.$r2"},"/ev",{"temp=":"$r"},{"->":".^.^.3.s"},[{"#n":"$r2"}],"\n","^My voice I mean. Can you hear me okay?","\n",{"#f":5}],"c-2":["ev",{"^->":"Start.0.c-2.$r2"},"/ev",{"temp=":"$r"},{"->":".^.^.4.s"},[{"#n":"$r2"}],"\n","^Okay good. I was told it would be hard to understand true intentions today. Thought it might be regarding the phone. Anyhoo, its Me.","\n",{"#f":5}],"c-3":["ev",{"^->":"Start.0.c-3.$r2"},"/ev",{"temp=":"$r"},{"->":".^.^.5.s"},[{"#n":"$r2"}],"^ Ma'am, I'm sorry but i'll need your name to assist you today.","\n","^Oh! I'm so sorry! I thought you were the other gentleman. Hello my new friend! My name is Chamomile. Like the Tea.","\n",{"#f":5}],"c-4":["ev",{"^->":"Start.0.c-4.$r2"},"/ev",{"temp=":"$r"},{"->":".^.^.6.s"},[{"#n":"$r2"}],"^ How can I help you today?","\n","^Why, I can't log in to my prayer chain. I have to make sure my followers know their futures today. What ever shall they do with the uncertainty??","\n",{"#f":5}],"c-5":["ev",{"^->":"Start.0.c-5.$r2"},"/ev",{"temp=":"$r"},{"->":".^.^.7.s"},[{"#n":"$r2"}],"^ is to test the validity of your account.","\n","^I'm sorry, but I dont know what that means.","\n",{"#f":5}],"c-6":["ev",{"^->":"Start.0.c-6.$r2"},"/ev",{"temp=":"$r"},{"->":".^.^.8.s"},[{"#n":"$r2"}],"^ Im going to send you a short list of your security questions. Please fill them out while I look at your details.","\n",{"->":"Start"},{"#f":5}]}],{"#f":1}],"TaskFailed":["^It doesn't seem to be working. Am i doing these wrong? I swear it is MY account!","\n","^oh my, today really isnt my day it seems. i'm am just not getting these. you know, is your day going just as bad as mine?","\n",{"#f":1}],"TaskSuccess":[["^I think thats all of them. Now, since we've just met, tell me about yourself. Hows your day going?","\n",["ev",{"^->":"TaskSuccess.0.2.$r1"},{"temp=":"$r"},"str",{"->":".^.s"},[{"#n":"$r1"}],"/str","/ev",{"*":".^.^.c-0","flg":18},{"s":["^It's...",{"->":"$r","var":true},null]}],{"*":".^.c-1","flg":16},["ev",{"^->":"TaskSuccess.0.4.$r1"},{"temp=":"$r"},"str",{"->":".^.s"},[{"#n":"$r1"}],"/str","/ev",{"*":".^.^.c-2","flg":18},{"s":["^Help myself...",{"->":"$r","var":true},null]}],["ev",{"^->":"TaskSuccess.0.5.$r1"},{"temp=":"$r"},"str",{"->":".^.s"},[{"#n":"$r1"}],"/str","/ev",{"*":".^.^.c-3","flg":18},{"s":["^Are you listening to me?",{"->":"$r","var":true},null]}],["ev",{"^->":"TaskSuccess.0.6.$r1"},{"temp=":"$r"},"str",{"->":".^.s"},[{"#n":"$r1"}],"/str","/ev",{"*":".^.^.c-4","flg":18},{"s":["^My own way...?",{"->":"$r","var":true},null]}],["ev",{"^->":"TaskSuccess.0.7.$r1"},{"temp=":"$r"},"str",{"->":".^.s"},[{"#n":"$r1"}],"/str","/ev",{"*":".^.^.c-5","flg":18},{"s":["^You aren't even hearing me...",{"->":"$r","var":true},null]}],["ev",{"^->":"TaskSuccess.0.8.$r1"},{"temp=":"$r"},"str",{"->":".^.s"},[{"#n":"$r1"}],"/str","/ev",{"*":".^.^.c-6","flg":18},{"s":["^Ma'am, im sorry",{"->":"$r","var":true},null]}],["ev",{"^->":"TaskSuccess.0.9.$r1"},{"temp=":"$r"},"str",{"->":".^.s"},[{"#n":"$r1"}],"/str","/ev",{"*":".^.^.c-7","flg":18},{"s":["^Journey of...",{"->":"$r","var":true},null]}],["ev",{"^->":"TaskSuccess.0.10.$r1"},{"temp=":"$r"},"str",{"->":".^.s"},[{"#n":"$r1"}],"/str","/ev",{"*":".^.^.c-8","flg":18},{"s":["^Personally, i feel",{"->":"$r","var":true},null]}],["ev",{"^->":"TaskSuccess.0.11.$r1"},{"temp=":"$r"},"str",{"->":".^.s"},[{"#n":"$r1"}],"/str","/ev",{"*":".^.^.c-9","flg":18},{"s":["^i...",{"->":"$r","var":true},null]}],["ev",{"^->":"TaskSuccess.0.12.$r1"},{"temp=":"$r"},"str",{"->":".^.s"},[{"#n":"$r1"}],"/str","/ev",{"*":".^.^.c-10","flg":18},{"s":["^i mean... ",{"->":"$r","var":true},null]}],["ev",{"^->":"TaskSuccess.0.13.$r1"},{"temp=":"$r"},"str",{"->":".^.s"},[{"#n":"$r1"}],"/str","/ev",{"*":".^.^.c-11","flg":18},{"s":["^what?",{"->":"$r","var":true},null]}],["ev",{"^->":"TaskSuccess.0.14.$r1"},{"temp=":"$r"},"str",{"->":".^.s"},[{"#n":"$r1"}],"/str","/ev",{"*":".^.^.c-12","flg":18},{"s":["^I don't think i should discuss my day with you.",{"->":"$r","var":true},null]}],["ev",{"^->":"TaskSuccess.0.15.$r1"},{"temp=":"$r"},"str",{"->":".^.s"},[{"#n":"$r1"}],"/str","/ev",{"*":".^.^.c-13","flg":18},{"s":["^We can't hang up before you do ma'am.",{"->":"$r","var":true},null]}],["ev",{"^->":"TaskSuccess.0.16.$r1"},{"temp=":"$r"},"str",{"->":".^.s"},[{"#n":"$r1"}],"/str","/ev",{"*":".^.^.c-14","flg":18},{"s":["^That sounds very frustraiting Ma'am.",{"->":"$r","var":true},null]}],{"c-0":["ev",{"^->":"TaskSuccess.0.c-0.$r2"},"/ev",{"temp=":"$r"},{"->":".^.^.2.s"},[{"#n":"$r2"}],"^Been quite the day. i am chained to my chair, and there is some shadow creature making sure i talk to you!","\n","^Oh my, thats quite the response! Keep going! What else?","\n",{"#f":5}],"c-1":["^I.. okay, well id really like to get out of here! Please!","\n","^Ha ha! There is so much energy there! So much gusto! My, thats perfect! Okay, and what can you do to change that? How can we help you to help yourself?","\n",{"#f":5}],"c-2":["ev",{"^->":"TaskSuccess.0.c-2.$r2"},"/ev",{"temp=":"$r"},{"->":".^.^.4.s"},[{"#n":"$r2"}],"\n",{"#f":5}],"c-3":["ev",{"^->":"TaskSuccess.0.c-3.$r2"},"/ev",{"temp=":"$r"},{"->":".^.^.5.s"},[{"#n":"$r2"}],"\n","^You have so much energy for your goals, and thats beautiful. Now you need to realise for yourself how you can bring ACTION to the words you are saying in your own way.","\n",{"#f":5}],"c-4":["ev",{"^->":"TaskSuccess.0.c-4.$r2"},"/ev",{"temp=":"$r"},{"->":".^.^.6.s"},[{"#n":"$r2"}],"\n",{"#f":5}],"c-5":["ev",{"^->":"TaskSuccess.0.c-5.$r2"},"/ev",{"temp=":"$r"},{"->":".^.^.7.s"},[{"#n":"$r2"}],"\n","^Nobody can give you the power to change your life. Only you can do that. You have to decide for yourself that you want change, and take it!","\n",{"#f":5}],"c-6":["ev",{"^->":"TaskSuccess.0.c-6.$r2"},"/ev",{"temp=":"$r"},{"->":".^.^.8.s"},[{"#n":"$r2"}],"^, i think i made a mistake.","\n","^No no! You have begun the journey of healing.","\n",{"#f":5}],"c-7":["ev",{"^->":"TaskSuccess.0.c-7.$r2"},"/ev",{"temp=":"$r"},{"->":".^.^.9.s"},[{"#n":"$r2"}],"^ I just said i was... I am extreamly confused Ma'am.","\n","^Confused? That means you are doing well! But maybe you are right. Am i rushing you?","\n",{"#f":5}],"c-8":["ev",{"^->":"TaskSuccess.0.c-8.$r2"},"/ev",{"temp=":"$r"},{"->":".^.^.10.s"},[{"#n":"$r2"}],"^ you are pushing me.","\n","^But if you aren't pushed, would you ever make progress?","\n",{"#f":5}],"c-9":["ev",{"^->":"TaskSuccess.0.c-9.$r2"},"/ev",{"temp=":"$r"},{"->":".^.^.11.s"},[{"#n":"$r2"}],"\n","^Perhaps some more encouragement? some proof of change being possible?","\n",{"#f":5}],"c-10":["ev",{"^->":"TaskSuccess.0.c-10.$r2"},"/ev",{"temp=":"$r"},{"->":".^.^.12.s"},[{"#n":"$r2"}],"\n","^A reading!","\n",{"#f":5}],"c-11":["ev",{"^->":"TaskSuccess.0.c-11.$r2"},"/ev",{"temp=":"$r"},{"->":".^.^.13.s"},[{"#n":"$r2"}],"\n",{"->":"tarotReading"},{"#f":5}],"c-12":["ev",{"^->":"TaskSuccess.0.c-12.$r2"},"/ev",{"temp=":"$r"},{"->":".^.^.14.s"},[{"#n":"$r2"}],"\n","^Oh... Oh well, okay then. May i tell you about my day?","\n",{"#f":5}],"c-13":["ev",{"^->":"TaskSuccess.0.c-13.$r2"},"/ev",{"temp=":"$r"},{"->":".^.^.15.s"},[{"#n":"$r2"}],"\n","^Okay well, thats something at least. So, I wake up right, and Imagine my suprise when i cant start my morning forcast. So i check the cards, and they say there is a \"Data Leek\" and my \"Account\" cant be \"Used\". As you can imagine, i was very frustraited.","\n",{"#f":5}],"c-14":["ev",{"^->":"TaskSuccess.0.c-14.$r2"},"/ev",{"temp=":"$r"},{"->":".^.^.16.s"},[{"#n":"$r2"}],"\n","^Indeed it was! And so i of course had to ask the cards. You know what i mean. Straighten things out a bit in my head... You Do know what i mean right?","\n","^Ask the Cards...? I... I mean not really. im sorry.","\n",{"#f":5}]}],{"#f":1}],"tarotReading":[["^Oh! Well, i of course mean the Tarot. Normally i use a Thelema selection, but i don't imagine that would be pertinant to assume the use of here. a Smith-Waite Major Arcana Deck is ideal for introductions.","\n",["ev",{"^->":"tarotReading.0.2.$r1"},{"temp=":"$r"},"str",{"->":".^.s"},[{"#n":"$r1"}],"/str","/ev",{"*":".^.^.c-0","flg":18},{"s":["^And you wish to do this over the phone Ma'am?",{"->":"$r","var":true},null]}],["ev",{"^->":"tarotReading.0.3.$r1"},{"temp=":"$r"},"str",{"->":".^.s"},[{"#n":"$r1"}],"/str","/ev",{"*":".^.^.c-1","flg":18},{"s":["^i mean in theory, but...",{"->":"$r","var":true},null]}],["ev",{"^->":"tarotReading.0.4.$r1"},{"temp=":"$r"},"str",{"->":".^.s"},[{"#n":"$r1"}],"/str","/ev",{"*":".^.^.c-2","flg":18},{"s":["^I'd rather we just stopped all this Ma'am. Please.",{"->":"$r","var":true},null]}],["ev",{"^->":"tarotReading.0.5.$r1"},{"temp=":"$r"},"str",{"->":".^.s"},[{"#n":"$r1"}],"/str","/ev",{"*":".^.^.c-3","flg":18},{"s":["^I will. Thank you...",{"->":"$r","var":true},null]}],["ev",{"^->":"tarotReading.0.6.$r1"},{"temp=":"$r"},"str",{"->":".^.s"},[{"#n":"$r1"}],"/str","/ev",{"*":".^.^.c-4","flg":18},{"s":["^Thank you Chamomile",{"->":"$r","var":true},null]}],["ev",{"^->":"tarotReading.0.7.$r1"},{"temp=":"$r"},"str",{"->":".^.s"},[{"#n":"$r1"}],"/str","/ev",{"*":".^.^.c-5","flg":18},{"s":["^Okay. ",{"->":"$r","var":true},null]}],["ev",{"^->":"tarotReading.0.8.$r1"},{"temp=":"$r"},"str",{"->":".^.s"},[{"#n":"$r1"}],"/str","/ev",{"*":".^.^.c-6","flg":18},{"s":["^I think its even true.",{"->":"$r","var":true},null]}],["ev",{"^->":"tarotReading.0.9.$r1"},{"temp=":"$r"},"str",{"->":".^.s"},[{"#n":"$r1"}],"/str","/ev",{"*":".^.^.c-7","flg":18},{"s":["^I think so.",{"->":"$r","var":true},null]}],["ev",{"^->":"tarotReading.0.10.$r1"},{"temp=":"$r"},"str",{"->":".^.s"},[{"#n":"$r1"}],"/str","/ev",{"*":".^.^.c-8","flg":18},{"s":["^Oh my? What?",{"->":"$r","var":true},null]}],["ev",{"^->":"tarotReading.0.11.$r1"},{"temp=":"$r"},"str",{"->":".^.s"},[{"#n":"$r1"}],"/str","/ev",{"*":".^.^.c-9","flg":18},{"s":["^I mean, that...",{"->":"$r","var":true},null]}],["ev",{"^->":"tarotReading.0.12.$r1"},{"temp=":"$r"},"str",{"->":".^.s"},[{"#n":"$r1"}],"/str","/ev",{"*":".^.^.c-10","flg":18},{"s":["^Well that doesnt better...",{"->":"$r","var":true},null]}],["ev",{"^->":"tarotReading.0.13.$r1"},{"temp=":"$r"},"str",{"->":".^.s"},[{"#n":"$r1"}],"/str","/ev",{"*":".^.^.c-11","flg":18},{"s":["^What? What does that mean?",{"->":"$r","var":true},null]}],["ev",{"^->":"tarotReading.0.14.$r1"},{"temp=":"$r"},"str",{"->":".^.s"},[{"#n":"$r1"}],"/str","/ev",{"*":".^.^.c-12","flg":18},{"s":["^A sword??? i cant use a sword...",{"->":"$r","var":true},null]}],["ev",{"^->":"tarotReading.0.15.$r1"},{"temp=":"$r"},"str",{"->":".^.s"},[{"#n":"$r1"}],"/str","/ev",{"*":".^.^.c-13","flg":18},{"s":["^i..oh...heh sorry...",{"->":"$r","var":true},null]}],["ev",{"^->":"tarotReading.0.16.$r1"},{"temp=":"$r"},"str",{"->":".^.s"},[{"#n":"$r1"}],"/str","/ev",{"*":".^.^.c-14","flg":18},{"s":["^Ah, so...the seven of swords?",{"->":"$r","var":true},null]}],["ev",{"^->":"tarotReading.0.17.$r1"},{"temp=":"$r"},"str",{"->":".^.s"},[{"#n":"$r1"}],"/str","/ev",{"*":".^.^.c-15","flg":18},{"s":["^a future of perhaps...hmm, thats incredibly cryptic",{"->":"$r","var":true},null]}],["ev",{"^->":"tarotReading.0.18.$r1"},{"temp=":"$r"},"str",{"->":".^.s"},[{"#n":"$r1"}],"/str","/ev",{"*":".^.^.c-16","flg":18},{"s":["^i mean... thank you?",{"->":"$r","var":true},null]}],["ev",{"^->":"tarotReading.0.19.$r1"},{"temp=":"$r"},"str",{"->":".^.s"},[{"#n":"$r1"}],"/str","/ev",{"*":".^.^.c-17","flg":18},{"s":["^Well, i work for OSOS",{"->":"$r","var":true},null]}],["ev",{"^->":"tarotReading.0.20.$r1"},{"temp=":"$r"},"str",{"->":".^.s"},[{"#n":"$r1"}],"/str","/ev",{"*":".^.^.c-18","flg":18},{"s":["^i... what?",{"->":"$r","var":true},null]}],{"c-0":["ev",{"^->":"tarotReading.0.c-0.$r2"},"/ev",{"temp=":"$r"},{"->":".^.^.2.s"},[{"#n":"$r2"}],"\n","^of course! Then it can guide you forward. Now, im just shuffling the deck here. Then im going to do a short draw of three cards, okay? and then the cards i draw will have meaning, depending on the card and the order. Does that make sense?","\n",{"#f":5}],"c-1":["ev",{"^->":"tarotReading.0.c-1.$r2"},"/ev",{"temp=":"$r"},{"->":".^.^.3.s"},[{"#n":"$r2"}],"\n","^Don't worry. It'll all make sense in just a minute.","\n",{"#f":5}],"c-2":["ev",{"^->":"tarotReading.0.c-2.$r2"},"/ev",{"temp=":"$r"},{"->":".^.^.4.s"},[{"#n":"$r2"}],"\n","^Well... I can't say im not dissapointed. You were making such good progress. But i of course will respect your intentions and your privacy. I hope you have a long think about what you want.","\n",{"#f":5}],"c-3":["ev",{"^->":"tarotReading.0.c-3.$r2"},"/ev",{"temp=":"$r"},{"->":".^.^.5.s"},[{"#n":"$r2"}],"\n","^Call me Chamomile.","\n",{"#f":5}],"c-4":["ev",{"^->":"tarotReading.0.c-4.$r2"},"/ev",{"temp=":"$r"},{"->":".^.^.6.s"},[{"#n":"$r2"}],"\n","^It was a pleasure.","\n","end",{"#f":5}],"c-5":["ev",{"^->":"tarotReading.0.c-5.$r2"},"/ev",{"temp=":"$r"},{"->":".^.^.7.s"},[{"#n":"$r2"}],"^I trust you.","\n","^Well thank you. Thats very kind.","\n",{"#f":5}],"c-6":["ev",{"^->":"tarotReading.0.c-6.$r2"},"/ev",{"temp=":"$r"},{"->":".^.^.8.s"},[{"#n":"$r2"}],"\n","^Well thats rather sweet. Okay. i am done shuffling. So i am going to draw three cards for you from this deck i have here. This first card will be signifying your past. something to speak towards where you have come from. trials that have passed over you. Make sense?","\n",{"#f":5}],"c-7":["ev",{"^->":"tarotReading.0.c-7.$r2"},"/ev",{"temp=":"$r"},{"->":".^.^.9.s"},[{"#n":"$r2"}],"\n","^Good, and ...Oh my...","\n",{"#f":5}],"c-8":["ev",{"^->":"tarotReading.0.c-8.$r2"},"/ev",{"temp=":"$r"},{"->":".^.^.10.s"},[{"#n":"$r2"}],"\n","^The Tower. Something signifying Distress and Adversity. A Large change. it can be good, but not as a flat first draw. You have seen misery leding you to here. pain and suffering? something looming over you?","\n",{"#f":5}],"c-9":["ev",{"^->":"tarotReading.0.c-9.$r2"},"/ev",{"temp=":"$r"},{"->":".^.^.11.s"},[{"#n":"$r2"}],"\n","^Oh my, that isnt a good start is it. Lets move on. Its got to get better... Oh okay. So here is the High priestess. Now she is interesting, especially in your present. She can mean many things, not as binary as the Tower. She is full of mystery, and secretive. You are surrounded by confusion? things unknown to you, yet known to others. You are unknown, even to yourself...","\n",{"#f":5}],"c-10":["ev",{"^->":"tarotReading.0.c-10.$r2"},"/ev",{"temp=":"$r"},{"->":".^.^.12.s"},[{"#n":"$r2"}],"\n","^You are full of sadness and mystery my friend. what an interesting read. two of the major arcana as well. hmm...","\n",{"#f":5}],"c-11":["ev",{"^->":"tarotReading.0.c-11.$r2"},"/ev",{"temp=":"$r"},{"->":".^.^.13.s"},[{"#n":"$r2"}],"\n","^Hmm? oh im sorry dear. Lets see your third one then...Oooh swords...","\n",{"#f":5}],"c-12":["ev",{"^->":"tarotReading.0.c-12.$r2"},"/ev",{"temp=":"$r"},{"->":".^.^.14.s"},[{"#n":"$r2"}],"\n","^Oh no! Hahah Not a real sword no. The Seven of Swords. a card from the deck again.","\n",{"#f":5}],"c-13":["ev",{"^->":"tarotReading.0.c-13.$r2"},"/ev",{"temp=":"$r"},{"->":".^.^.15.s"},[{"#n":"$r2"}],"^ i feel a little silly now.","\n","^Don't beat your self up. its hard without being able to see the cards. the art is rather pretty on these ones too.","\n",{"#f":5}],"c-14":["ev",{"^->":"tarotReading.0.c-14.$r2"},"/ev",{"temp=":"$r"},{"->":".^.^.16.s"},[{"#n":"$r2"}],"\n","^oh Yes of course! So, the seven of swords is a card about uncertainty and planning. In your future is a plan or design that has a strong maybe in it. Something that will succeed. It hangs in the balance, easily swayed with pushes either way. It speaks of attemping things, with hope and confidance, but also of quarrelling, arguing, and annoyance. its a future of perhaps.","\n",{"#f":5}],"c-15":["ev",{"^->":"tarotReading.0.c-15.$r2"},"/ev",{"temp=":"$r"},{"->":".^.^.17.s"},[{"#n":"$r2"}],"\n","^Well, thats quite the future you have there.","\n",{"#f":5}],"c-16":["ev",{"^->":"tarotReading.0.c-16.$r2"},"/ev",{"temp=":"$r"},{"->":".^.^.18.s"},[{"#n":"$r2"}],"^ i guess?","\n","^oh, its not a compliment. it sounds like you have a lot going on. In your head and your heart. Where did you say you worked again?","\n",{"#f":5}],"c-17":["ev",{"^->":"tarotReading.0.c-17.$r2"},"/ev",{"temp=":"$r"},{"->":".^.^.19.s"},[{"#n":"$r2"}],"^ obviously. The local branch, i believe.","\n","^Great. I have written that down. Maybe i'll see in person some day?","\n",{"#f":5}],"c-18":["ev",{"^->":"tarotReading.0.c-18.$r2"},"/ev",{"temp=":"$r"},{"->":".^.^.20.s"},[{"#n":"$r2"}],"\n",{"->":"SucessGameEnding"},{"->":"FailGameEnding"},{"#f":5}]}],{"#f":1}],"SucessGameEnding":[["^Well, i have to go. iv missed my first stream, but the second one is just as important. Im finding the latent energies of the internet and calming them for the masses. Thank you again for the help","\n",["ev",{"^->":"SucessGameEnding.0.2.$r1"},{"temp=":"$r"},"str",{"->":".^.s"},[{"#n":"$r1"}],"/str","/ev",{"*":".^.^.c-0","flg":18},{"s":["^It...it was my pleasure",{"->":"$r","var":true},null]}],{"c-0":["ev",{"^->":"SucessGameEnding.0.c-0.$r2"},"/ev",{"temp=":"$r"},{"->":".^.^.2.s"},[{"#n":"$r2"}],"^. Thank you Chammomile.","\n","^Bye!","\n","end",{"#f":5}]}],{"#f":1}],"FailGameEnding":[["^Well, i have to go pick flowers. If i make a tincture of lambs bredth and foxglove, and bathe my modem, maybe my account will fix itself. Thank you for the lovely chat, and for trying to help.","\n",["ev",{"^->":"FailGameEnding.0.2.$r1"},{"temp=":"$r"},"str",{"->":".^.s"},[{"#n":"$r1"}],"/str","/ev",{"*":".^.^.c-0","flg":18},{"s":["^I think it was truly my pleasure.",{"->":"$r","var":true},null]}],{"c-0":["ev",{"^->":"FailGameEnding.0.c-0.$r2"},"/ev",{"temp=":"$r"},{"->":".^.^.2.s"},[{"#n":"$r2"}],"\n","^Heh, i think so too. Be well!","\n","end",{"#f":5}]}],{"#f":1}],"global decl":["ev",true,{"VAR=":"BeingWatched"},0,{"VAR=":"BossSuspicionCounter"},0,{"VAR=":"HelpCounter"},false,{"VAR=":"bTaskFail"},false,{"VAR=":"bTaskSuccess"},"/ev","end",null],"#f":1}],"listDefs":{}}